AUTHORS
CHANGES.txt
INSTALL
LICENSE
MANIFEST.in
README.rst
REQUIRED
setup.cfg
setup.py
setup_utils.py
eventor/__init__.py
eventor.egg-info/PKG-INFO
eventor.egg-info/SOURCES.txt
eventor.egg-info/dependency_links.txt
eventor.egg-info/requires.txt
eventor.egg-info/top_level.txt
eventor/bin/__init__.py
eventor/bin/eventor_agent.py
eventor/bin/eventor_agent.py.sav
eventor/lib/__init__.py
eventor/lib/assoc.py
eventor/lib/cmd.py
eventor/lib/conf_handler.py
eventor/lib/dbapi.py
eventor/lib/dbschema.py
eventor/lib/delay.py
eventor/lib/engine.py
eventor/lib/etypes.py
eventor/lib/event.py
eventor/lib/eventor_types.py
eventor/lib/sqladburl.py
eventor/lib/step.py
eventor/lib/utils.py
eventor/lib/vrp.py
eventor/lib/vrpdb.py