Metadata-Version: 1.1
Name: eventor
Version: 5.1.9
Summary: eventor is a python programming facility to program event based sequence of activities
Home-page: https://github.com/Acrisel/eventor
Author: Acrisel Team
Author-email: support@acrisel.com
License: MIT
Keywords: project,virtualenv,parameters
Platform: UNKNOWN
Classifier: Development Status :: 5 - Production/Stable
Classifier: Environment :: Other Environment
Classifier: Intended Audience :: Developers
Classifier: License :: OSI Approved :: MIT License
Classifier: Operating System :: OS Independent
Classifier: Programming Language :: Python
Classifier: Programming Language :: Python :: 3
Classifier: Programming Language :: Python :: 3.2
Classifier: Programming Language :: Python :: 3.3
Classifier: Programming Language :: Python :: 3.4
Classifier: Programming Language :: Python :: 3.5
Classifier: Programming Language :: Python :: 3.6
Classifier: Topic :: Software Development :: Libraries :: Application Frameworks
